{
  "form_number": 1,
  "pdf_filename": "cms1500_form_0001.pdf",
  "png_filename": "cms1500_form_0001.png",
  "generated_date": "1995-11-29T12:51:36.657450",
  "form_data": {
    "box_1_insurance_type_index": 2,
    "box_1_insurance_type_name": "Tricare/Champus",
    "box_1a_insured_id_number": "vC14511489",
    "box_2_patient_name": "Justin Dalton",
    "box_3_patient_birth_month": "10",
    "box_3_patient_birth_day": "31",
    "box_3_patient_birth_year": "69",
    "box_3_patient_sex": "F",
    "box_4_insured_name": "Justin Dalton",
    "box_5_patient_street": "626 Price Shore Apt. 068",
    "box_5_patient_city": "Danamouth",
    "box_5_patient_state": "SC",
    "box_5_patient_zip": "20248",
    "box_5_patient_area_code": "819",
    "box_5_patient_phone": "468-0608",
    "box_6_patient_relationship_to_insured": "O",
    "box_7_insured_street": "8080 Melissa Islands Suite 499",
    "box_7_insured_city": "Pattonview",
    "box_7_insured_state": "IL",
    "box_7_insured_zip": "68321",
    "box_7_insured_phone_area": "910",
    "box_7_insured_phone": "807-9223",
    "box_8_reserved_for_nucc_use": "",
    "box_9_other_insured_name": "Sean Gill",
    "box_9a_other_insured_policy_number": "vy99096847",
    "box_9d_other_insurance_plan_name": "Humana",
    "box_10a_employment_related": "YES",
    "box_10b_auto_accident_related": "NO",
    "box_10c_other_accident_related": "YES",
    "box_10d_accident_place": "RI",
    "box_11_insured_group_number": "GRP735140",
    "box_11a_insured_birth_month": "10",
    "box_11a_insured_birth_day": "31",
    "box_11a_insured_birth_year": "50",
    "box_11a_insured_sex": "MALE",
    "box_11c_insurance_plan_name": "High Deductible Health Plan",
    "box_11d_other_health_benefit_plan": "YES",
    "box_12_patient_signature": "Patient Signature on File",
    "box_12_patient_signature_date": "09/06/25",
    "box_13_insured_signature": "Signature on File",
    "box_14_current_illness_month": "11",
    "box_14_current_illness_day": "04",
    "box_14_current_illness_year": "24",
    "box_15_other_date_month": "",
    "box_15_other_date_day": "",
    "box_15_other_date_year": "",
    "box_16_work_unable_from_month": "",
    "box_16_work_unable_from_day": "",
    "box_16_work_unable_from_year": "",
    "box_16_work_unable_to_month": "",
    "box_16_work_unable_to_day": "",
    "box_16_work_unable_to_year": "",
    "box_17_referring_provider_name": "",
    "box_17a_referring_provider_npi": "",
    "box_17b_referring_provider_qualifier": "",
    "box_18_hospitalization_from_month": "",
    "box_18_hospitalization_from_day": "",
    "box_18_hospitalization_from_year": "",
    "box_18_hospitalization_to_month": "",
    "box_18_hospitalization_to_day": "",
    "box_18_hospitalization_to_year": "",
    "box_20_outside_lab": "NO",
    "box_22_medicaid_resubmission": "",
    "box_22_original_reference_number": "REF4897535",
    "box_23_prior_authorization": "PA80880930",
    "box_25_federal_tax_id": "98-9594768",
    "box_25_tax_id_type": "EIN",
    "box_26_patient_account_number": "6377-113-4525",
    "box_27_accept_assignment": "NO",
    "box_28_total_charge": "1412.00",
    "box_29_amount_paid": "838.00",
    "box_30_balance_due": "574.00",
    "box_31_physician_signature": "Dr. Daniel Valenzuela, MD",
    "box_31_physician_signature_date": "09/03/25",
    "box_32_service_facility_name": "Regional Medical Center",
    "box_32_service_facility_street": "Unit 1195 Box 5517, DPO AP 62363",
    "box_32_service_facility_location": "Meadowston, PA 42239",
    "box_33_billing_provider_name": "Dr. Daniel Valenzuela, MD",
    "box_33_billing_provider_address": "4166 Owens Corners, North Sherriport, PA 73780",
    "box_33_billing_provider_phone": "612-1028",
    "box_33_billing_provider_phone_area": "223",
    "box_33a_billing_provider_npi": "8084059376",
    "insurance_company_name": "UnitedHealth",
    "insurance_company_address": "9900 Bren Rd E, Minnetonka, MN 55343",
    "insurance_id": "5771678286",
    "insurance_address2": "Suite 777",
    "insurance_city_state_zip": "",
    "pin": "",
    "pin1": "",
    "grp1": "078086",
    "doc_location": "",
    "num_diagnoses": 1,
    "num_service_lines": 5,
    "pt_street": "626 Price Shore Apt. 068",
    "pt_city": "Danamouth",
    "pt_state": "SC",
    "pt_zip": "20248",
    "pt_AreaCode": "819",
    "pt_phone": "468-0608",
    "birth_mm": "10",
    "birth_dd": "31",
    "birth_yy": "69",
    "ins_dob_mm": "10",
    "ins_dob_dd": "31",
    "ins_dob_yy": "50",
    "insurance_type_index": 2,
    "insurance_type_name": "Tricare/Champus",
    "sex": "F",
    "rel_to_ins": "O",
    "employment": "YES",
    "pt_auto_accident": "NO",
    "other_accident": "YES",
    "ins_sex": "MALE",
    "ins_benefit_plan": "YES",
    "lab": "NO",
    "ssn": "EIN",
    "assignment": "NO",
    "pt_name": "Justin Dalton",
    "pt_account": "6377-113-4525",
    "ins_name": "Justin Dalton",
    "ins_policy": "vC14511489",
    "doc_name": "Dr. Daniel Valenzuela, MD",
    "doc_street": "4166 Owens Corners, North Sherriport, PA 73780",
    "doc_phone": "612-1028",
    "doc_phone area": "223",
    "id_physician": "8084059376",
    "tax_id": "98-9594768",
    "t_charge": "1412.00",
    "amt_paid": "838.00",
    "charge": "574.00",
    "cur_ill_mm": "11",
    "cur_ill_dd": "04",
    "cur_ill_yy": "24",
    "sim_ill_mm": "",
    "sim_ill_dd": "",
    "sim_ill_yy": "",
    "work_mm_from": "",
    "work_dd_from": "",
    "work_yy_from": "",
    "work_mm_end": "",
    "work_dd_end": "",
    "work_yy_end": "",
    "hosp_mm_from": "",
    "hosp_dd_from": "",
    "hosp_yy_from": "",
    "hosp_mm_end": "",
    "hosp_dd_end": "",
    "hosp_yy_end": "",
    "accident_place": "RI",
    "other_ins_name": "Sean Gill",
    "other_ins_policy": "vy99096847",
    "other_ins_plan_name": "Humana",
    "prior_auth": "PA80880930",
    "original_ref": "REF4897535",
    "medicaid_resub": "",
    "ref_physician": "",
    "physician number 17a": "",
    "physician number 17a1": "",
    "pt_signature": "Patient Signature on File",
    "pt_date": "09/06/25",
    "physician_signature": "Dr. Daniel Valenzuela, MD",
    "physician_date": "09/03/25",
    "fac_name": "Regional Medical Center",
    "fac_street": "Unit 1195 Box 5517, DPO AP 62363",
    "fac_location": "Meadowston, PA 42239",
    "ins_street": "8080 Melissa Islands Suite 499",
    "ins_city": "Pattonview",
    "ins_state": "IL",
    "ins_zip": "68321",
    "ins_phone": "807-9223",
    "ins_phone area": "910",
    "NUCC USE": "",
    "ins_plan_name": "High Deductible Health Plan",
    "ins_signature": "Signature on File",
    "box_21_diagnosis_1_code": "J06.9",
    "box_21_diagnosis_1_description": "Acute upper respiratory infection, unspecified",
    "diagnosis1": "J06.9",
    "diagnosis1_description": "Acute upper respiratory infection, unspecified",
    "box_21_diagnosis_2_code": "",
    "box_21_diagnosis_2_description": "",
    "diagnosis2": "",
    "diagnosis2_description": "",
    "box_21_diagnosis_3_code": "",
    "box_21_diagnosis_3_description": "",
    "diagnosis3": "",
    "diagnosis3_description": "",
    "box_21_diagnosis_4_code": "",
    "box_21_diagnosis_4_description": "",
    "diagnosis4": "",
    "diagnosis4_description": "",
    "box_21_diagnosis_5_code": "",
    "box_21_diagnosis_5_description": "",
    "diagnosis5": "",
    "diagnosis5_description": "",
    "box_21_diagnosis_6_code": "",
    "box_21_diagnosis_6_description": "",
    "diagnosis6": "",
    "diagnosis6_description": "",
    "box_21_diagnosis_7_code": "",
    "box_21_diagnosis_7_description": "",
    "diagnosis7": "",
    "diagnosis7_description": "",
    "box_21_diagnosis_8_code": "",
    "box_21_diagnosis_8_description": "",
    "diagnosis8": "",
    "diagnosis8_description": "",
    "box_21_diagnosis_9_code": "",
    "box_21_diagnosis_9_description": "",
    "diagnosis9": "",
    "diagnosis9_description": "",
    "box_21_diagnosis_10_code": "",
    "box_21_diagnosis_10_description": "",
    "diagnosis10": "",
    "diagnosis10_description": "",
    "box_21_diagnosis_11_code": "",
    "box_21_diagnosis_11_description": "",
    "diagnosis11": "",
    "diagnosis11_description": "",
    "box_21_diagnosis_12_code": "",
    "box_21_diagnosis_12_description": "",
    "diagnosis12": "",
    "diagnosis12_description": "",
    "box_24e_diagnosis_pointer_1": "A",
    "diag1": "A",
    "box_24e_diagnosis_pointer_2": "",
    "diag2": "",
    "box_24e_diagnosis_pointer_3": "",
    "diag3": "",
    "box_24e_diagnosis_pointer_4": "",
    "diag4": "",
    "box_24e_diagnosis_pointer_5": "",
    "diag5": "",
    "box_24e_diagnosis_pointer_6": "",
    "diag6": "",
    "cpt1": "90471",
    "cpt1_description": "Medical service for 90471",
    "mod1": "",
    "mod1a": "25",
    "mod1b": "",
    "mod1c": "26",
    "place1": "99",
    "type1": "V",
    "emg1": "",
    "day1": "",
    "cpt2": "11042",
    "cpt2_description": "Medical service for 11042",
    "mod2": "",
    "mod2a": "",
    "mod2b": "TC",
    "mod2c": "",
    "place2": "23",
    "type2": "2",
    "emg2": "",
    "day2": "",
    "cpt3": "36415",
    "cpt3_description": "Medical service for 36415",
    "mod3": "",
    "mod3a": "26",
    "mod3b": "",
    "mod3c": "",
    "place3": "52",
    "type3": "5",
    "emg3": "",
    "day3": "",
    "cpt4": "99213",
    "cpt4_description": "Medical service for 99213",
    "mod4": "",
    "mod4a": "59",
    "mod4b": "",
    "mod4c": "",
    "place4": "61",
    "type4": "1",
    "emg4": "",
    "day4": "",
    "cpt5": "71020",
    "cpt5_description": "Medical service for 71020",
    "mod5": "",
    "mod5a": "",
    "mod5b": "",
    "mod5c": "",
    "place5": "55",
    "type5": "4",
    "emg5": "",
    "day5": "",
    "cpt6": "",
    "mod6": "",
    "mod6a": "",
    "mod6b": "",
    "mod6c": "",
    "place6": "",
    "type6": "",
    "emg6": "",
    "day6": "",
    "sv1_mm_from": "09",
    "sv1_dd_from": "01",
    "sv1_yy_from": "25",
    "sv1_mm_end": "09",
    "sv1_dd_end": "01",
    "sv1_yy_end": "25",
    "sv2_mm_from": "08",
    "sv2_dd_from": "16",
    "sv2_yy_from": "25",
    "sv2_mm_end": "08",
    "sv2_dd_end": "16",
    "sv2_yy_end": "25",
    "sv3_mm_from": "08",
    "sv3_dd_from": "11",
    "sv3_yy_from": "25",
    "sv3_mm_end": "08",
    "sv3_dd_end": "11",
    "sv3_yy_end": "25",
    "sv4_mm_from": "08",
    "sv4_dd_from": "21",
    "sv4_yy_from": "25",
    "sv4_mm_end": "08",
    "sv4_dd_end": "21",
    "sv4_yy_end": "25",
    "sv5_mm_from": "08",
    "sv5_dd_from": "14",
    "sv5_yy_from": "25",
    "sv5_mm_end": "08",
    "sv5_dd_end": "14",
    "sv5_yy_end": "25",
    "sv6_mm_from": "",
    "sv6_dd_from": "",
    "sv6_yy_from": "",
    "sv6_mm_end": "",
    "sv6_dd_end": "",
    "sv6_yy_end": "",
    "ch1": "336.00",
    "ch2": "127.00",
    "ch3": "352.00",
    "ch4": "497.00",
    "ch5": "100.00",
    "ch6": "",
    "units1": "1",
    "units2": "1",
    "units3": "4",
    "units4": "1",
    "units5": "1",
    "units6": "",
    "Suppl": "",
    "Suppla": "SUP808",
    "Supplb": "",
    "Supplc": "",
    "Suppld": "",
    "Supple": "",
    "local1": "MED115",
    "local1a": "",
    "local2": "",
    "local2a": "",
    "local3": "",
    "local3a": "",
    "local4": "",
    "local4a": "",
    "local5": "",
    "local5a": "",
    "local6": "",
    "local6a": "",
    "epsdt1": "",
    "epsdt2": "",
    "epsdt3": "",
    "epsdt4": "",
    "epsdt5": "",
    "epsdt6": "",
    "plan1": "EMRG40",
    "plan2": "EMRG03",
    "plan3": "",
    "plan4": "",
    "plan5": "PREV96",
    "plan6": ""
  }
}